MANIFEST.in
README.md
requirements.txt
setup.py
django_polyencode/__init__.py
django_polyencode/admin.py
django_polyencode/models.py
django_polyencode/signals.py
django_polyencode.egg-info/PKG-INFO
django_polyencode.egg-info/SOURCES.txt
django_polyencode.egg-info/dependency_links.txt
django_polyencode.egg-info/not-zip-safe
django_polyencode.egg-info/requires.txt
django_polyencode.egg-info/top_level.txt
django_polyencode/management/__init__.py
django_polyencode/management/commands/__init__.py
django_polyencode/management/commands/import_extra_csv.py
django_polyencode/management/commands/import_mmqgis_csv.py
django_polyencode/management/commands/redefine_perimeter.py
django_polyencode/migrations/0001_initial.py
django_polyencode/migrations/0002_auto_20160912_1356.py
django_polyencode/migrations/0003_auto_20160912_1403.py
django_polyencode/migrations/0004_auto_20160916_0934.py
django_polyencode/migrations/0005_auto_20230131_1214.py
django_polyencode/migrations/__init__.py