Metadata-Version: 2.1
Name: django_polyencode
Version: 2.4
Summary: Geo data database structure for the Django web framework.
Home-page: https://github.com/codesyntax/django-geodata
Author: Urtzi Odriozola (Code Syntax http://codesyntax.com)
Author-email: uodriozola@codesyntax.com
Classifier: Development Status :: 5 - Production/Stable
Classifier: Environment :: Web Environment
Classifier: Framework :: Django
Classifier: Intended Audience :: Developers
Classifier: License :: OSI Approved :: BSD License
Classifier: Operating System :: OS Independent
Classifier: Programming Language :: Python
Classifier: Programming Language :: Python :: 3.9
Classifier: Programming Language :: Python :: 3.10
Classifier: Programming Language :: Python :: 3.11
Classifier: Topic :: Utilities
Requires-Dist: Django>=1.9
Requires-Dist: Shapely>=1.5.13
Requires-Dist: py-gpolyencode>=0.2.1
